PyHP8903A/PyHP8903A.py
PyHP8903A/__init__.py
PyHP8903A-0.3.dist-info/LICENSE
PyHP8903A-0.3.dist-info/METADATA
PyHP8903A-0.3.dist-info/WHEEL
PyHP8903A-0.3.dist-info/top_level.txt
PyHP8903A-0.3.dist-info/RECORD
