Metadata-Version: 2.1
Name: PyHP8903A
Version: 0.3
Summary: HP8903A python interface
Home-page: https://github.com/Minu-IU3IRR/PyHP8903A
Author: Manuel Minutello
License: MIT
License-File: LICENSE
Requires-Dist: PyAR488
